<?xml version="1.0" encoding="utf-8"?>

<sprites>

  <sprite name="debug" portrait="reds">

    <animations>
      <animation name="idle" direction="front">
        <frame duration="1">standing front</frame>
      </animation>

      <animation name="idle" direction="back">
        <frame duration="1">standing back</frame>
      </animation>
    </animations>

  </sprite>

  <sprite name="reds">

    <animations>
      <animation name="idle" direction="front">
        <frame duration="1">standing front</frame>
      </animation>

      <animation name="idle" direction="back">
        <frame duration="1">standing back</frame>
      </animation>
    </animations>

  </sprite>

  <sprite name="phil">

    <animations>
      <animation name="idle" direction="front">
        <frame duration="1">idle front</frame>
      </animation>

      <animation name="walk" direction="front">
        <frame duration="0.0625">walk1 front</frame>
        <frame duration="0.0625">idle front</frame>
        <frame duration="0.0625">walk2 front</frame>
        <frame duration="0.0625">idle front</frame>
      </animation>

      <animation name="idle" direction="back">
        <frame duration="1">idle back</frame>
      </animation>

      <animation name="walk" direction="back">
        <frame duration="0.0625">walk1 back</frame>
        <frame duration="0.0625">idle back</frame>
        <frame duration="0.0625">walk2 back</frame>
        <frame duration="0.0625">idle back</frame>
      </animation>
    </animations>
    
  </sprite>
  
</sprites>